.gitignore
.readthedocs.yaml
LICENSE
MANIFEST.in
README.md
pyproject.toml
pytest.ini
setup.py
.github/workflows/cicd.yml
docs/README.md
docs/conf.py
docs/index.rst
docs/tutorial/ProteomicsData_DIA_demo.xlsx
docs/tutorial/excel_read.py
docs/tutorial/tutorial.py
src/dsp_pandas/__init__.py
src/dsp_pandas/format.py
src/dsp_pandas/io.py
src/dsp_pandas.egg-info/PKG-INFO
src/dsp_pandas.egg-info/SOURCES.txt
src/dsp_pandas.egg-info/dependency_links.txt
src/dsp_pandas.egg-info/requires.txt
src/dsp_pandas.egg-info/top_level.txt
src/dsp_pandas/df/__init__.py
src/dsp_pandas/df/missing_data.py
tests/__init__.py
tests/test_format.py
tests/test_init.py
tests/test_io.py
tests/data/test.xlsx
tests/df/test_df.py
tests/df/test_missing_data.py